<annotation>
	<folder></folder>
	<filename>image_387_jpg.rf.c17ece7dc3b9a078e2449c3fe42aeaee.jpg</filename>
	<path>image_387_jpg.rf.c17ece7dc3b9a078e2449c3fe42aeaee.jpg</path>
	<source>
		<database>roboflow.com</database>
	</source>
	<size>
		<width>640</width>
		<height>640</height>
		<depth>3</depth>
	</size>
	<segmented>0</segmented>
	<object>
		<name>tomato</name>
		<pose>Unspecified</pose>
		<truncated>0</truncated>
		<difficult>0</difficult>
		<occluded>0</occluded>
		<bndbox>
			<xmin>588</xmin>
			<xmax>641</xmax>
			<ymin>127</ymin>
			<ymax>184</ymax>
		</bndbox>
	</object>
	<object>
		<name>tomato</name>
		<pose>Unspecified</pose>
		<truncated>0</truncated>
		<difficult>0</difficult>
		<occluded>0</occluded>
		<bndbox>
			<xmin>233</xmin>
			<xmax>276</xmax>
			<ymin>57</ymin>
			<ymax>117</ymax>
		</bndbox>
	</object>
	<object>
		<name>tomato</name>
		<pose>Unspecified</pose>
		<truncated>0</truncated>
		<difficult>0</difficult>
		<occluded>0</occluded>
		<bndbox>
			<xmin>268</xmin>
			<xmax>299</xmax>
			<ymin>75</ymin>
			<ymax>120</ymax>
		</bndbox>
	</object>
	<object>
		<name>tomato</name>
		<pose>Unspecified</pose>
		<truncated>0</truncated>
		<difficult>0</difficult>
		<occluded>0</occluded>
		<bndbox>
			<xmin>223</xmin>
			<xmax>261</xmax>
			<ymin>178</ymin>
			<ymax>220</ymax>
		</bndbox>
	</object>
	<object>
		<name>tomato</name>
		<pose>Unspecified</pose>
		<truncated>0</truncated>
		<difficult>0</difficult>
		<occluded>0</occluded>
		<bndbox>
			<xmin>187</xmin>
			<xmax>218</xmax>
			<ymin>176</ymin>
			<ymax>214</ymax>
		</bndbox>
	</object>
	<object>
		<name>tomato</name>
		<pose>Unspecified</pose>
		<truncated>0</truncated>
		<difficult>0</difficult>
		<occluded>0</occluded>
		<bndbox>
			<xmin>127</xmin>
			<xmax>178</xmax>
			<ymin>159</ymin>
			<ymax>205</ymax>
		</bndbox>
	</object>
	<object>
		<name>tomato</name>
		<pose>Unspecified</pose>
		<truncated>0</truncated>
		<difficult>0</difficult>
		<occluded>0</occluded>
		<bndbox>
			<xmin>133</xmin>
			<xmax>164</xmax>
			<ymin>286</ymin>
			<ymax>351</ymax>
		</bndbox>
	</object>
	<object>
		<name>tomato</name>
		<pose>Unspecified</pose>
		<truncated>0</truncated>
		<difficult>0</difficult>
		<occluded>0</occluded>
		<bndbox>
			<xmin>175</xmin>
			<xmax>221</xmax>
			<ymin>306</ymin>
			<ymax>368</ymax>
		</bndbox>
	</object>
	<object>
		<name>tomato</name>
		<pose>Unspecified</pose>
		<truncated>0</truncated>
		<difficult>0</difficult>
		<occluded>0</occluded>
		<bndbox>
			<xmin>113</xmin>
			<xmax>137</xmax>
			<ymin>185</ymin>
			<ymax>210</ymax>
		</bndbox>
	</object>
	<object>
		<name>tomato</name>
		<pose>Unspecified</pose>
		<truncated>0</truncated>
		<difficult>0</difficult>
		<occluded>0</occluded>
		<bndbox>
			<xmin>171</xmin>
			<xmax>189</xmax>
			<ymin>250</ymin>
			<ymax>272</ymax>
		</bndbox>
	</object>
	<object>
		<name>tomato</name>
		<pose>Unspecified</pose>
		<truncated>0</truncated>
		<difficult>0</difficult>
		<occluded>0</occluded>
		<bndbox>
			<xmin>215</xmin>
			<xmax>278</xmax>
			<ymin>372</ymin>
			<ymax>455</ymax>
		</bndbox>
	</object>
	<object>
		<name>tomato</name>
		<pose>Unspecified</pose>
		<truncated>0</truncated>
		<difficult>0</difficult>
		<occluded>0</occluded>
		<bndbox>
			<xmin>289</xmin>
			<xmax>332</xmax>
			<ymin>375</ymin>
			<ymax>429</ymax>
		</bndbox>
	</object>
	<object>
		<name>tomato</name>
		<pose>Unspecified</pose>
		<truncated>0</truncated>
		<difficult>0</difficult>
		<occluded>0</occluded>
		<bndbox>
			<xmin>298</xmin>
			<xmax>347</xmax>
			<ymin>424</ymin>
			<ymax>480</ymax>
		</bndbox>
	</object>
	<object>
		<name>tomato</name>
		<pose>Unspecified</pose>
		<truncated>0</truncated>
		<difficult>0</difficult>
		<occluded>0</occluded>
		<bndbox>
			<xmin>353</xmin>
			<xmax>412</xmax>
			<ymin>448</ymin>
			<ymax>527</ymax>
		</bndbox>
	</object>
	<object>
		<name>tomato</name>
		<pose>Unspecified</pose>
		<truncated>0</truncated>
		<difficult>0</difficult>
		<occluded>0</occluded>
		<bndbox>
			<xmin>380</xmin>
			<xmax>450</xmax>
			<ymin>521</ymin>
			<ymax>590</ymax>
		</bndbox>
	</object>
	<object>
		<name>tomato</name>
		<pose>Unspecified</pose>
		<truncated>0</truncated>
		<difficult>0</difficult>
		<occluded>0</occluded>
		<bndbox>
			<xmin>383</xmin>
			<xmax>418</xmax>
			<ymin>142</ymin>
			<ymax>187</ymax>
		</bndbox>
	</object>
	<metadata>
	</metadata>
</annotation>
